{
  "parent": "minecraft:recipes/root",
  "criteria": {
    "has_the_recipe": {
      "conditions": {
        "recipe": "indreb:recycling/tools/iron_shovel"
      },
      "trigger": "minecraft:recipe_unlocked"
    },
    "iron_shovel": {
      "conditions": {
        "items": [
          {
            "items": [
              "minecraft:iron_shovel"
            ]
          }
        ]
      },
      "trigger": "minecraft:inventory_changed"
    }
  },
  "requirements": [
    [
      "iron_shovel",
      "has_the_recipe"
    ]
  ],
  "rewards": {
    "recipes": [
      "indreb:recycling/tools/iron_shovel"
    ]
  }
}