{
  "variants": {
    "active=false,facing=north": {
      "model": "indreb:block/semifluid_generator"
    },
    "active=true,facing=north": {
      "model": "indreb:block/semifluid_generator_active"
    },
    "active=false,facing=south": {
      "model": "indreb:block/semifluid_generator",
      "y": 180
    },
    "active=true,facing=south": {
      "model": "indreb:block/semifluid_generator_active",
      "y": 180
    },
    "active=false,facing=west": {
      "model": "indreb:block/semifluid_generator",
      "y": 270
    },
    "active=true,facing=west": {
      "model": "indreb:block/semifluid_generator_active",
      "y": 270
    },
    "active=false,facing=east": {
      "model": "indreb:block/semifluid_generator",
      "y": 90
    },
    "active=true,facing=east": {
      "model": "indreb:block/semifluid_generator_active",
      "y": 90
    }
  }
}