{
  "parent": "minecraft:recipes/root",
  "criteria": {
    "clay": {
      "conditions": {
        "items": [
          {
            "items": [
              "minecraft:clay"
            ]
          }
        ]
      },
      "trigger": "minecraft:inventory_changed"
    },
    "has_the_recipe": {
      "conditions": {
        "recipe": "indreb:crushing/clay_clay_ball"
      },
      "trigger": "minecraft:recipe_unlocked"
    }
  },
  "requirements": [
    [
      "clay",
      "has_the_recipe"
    ]
  ],
  "rewards": {
    "recipes": [
      "indreb:crushing/clay_clay_ball"
    ]
  }
}