{
  "parent": "minecraft:recipes/root",
  "rewards": {
    "recipes": [
      "indreb:crushing/flowers/dandelion_yellow_dye"
    ]
  },
  "criteria": {
    "item": {
      "trigger": "minecraft:inventory_changed",
      "conditions": {
        "items": [
          {
            "items": [
              "minecraft:dandelion"
            ]
          }
        ]
      }
    },
    "has_the_recipe": {
      "trigger": "minecraft:recipe_unlocked",
      "conditions": {
        "recipe": "indreb:crushing/flowers/dandelion_yellow_dye"
      }
    }
  },
  "requirements": [
    [
      "item",
      "has_the_recipe"
    ]
  ]
}