{
  "parent": "minecraft:recipes/root",
  "rewards": {
    "recipes": [
      "indreb:compressing/block/snowball_snow_block"
    ]
  },
  "criteria": {
    "item": {
      "trigger": "minecraft:inventory_changed",
      "conditions": {
        "items": [
          {
            "items": [
              "minecraft:snowball"
            ]
          }
        ]
      }
    },
    "has_the_recipe": {
      "trigger": "minecraft:recipe_unlocked",
      "conditions": {
        "recipe": "indreb:compressing/block/snowball_snow_block"
      }
    }
  },
  "requirements": [
    [
      "item",
      "has_the_recipe"
    ]
  ]
}