{
  "parent": "minecraft:recipes/root",
  "rewards": {
    "recipes": [
      "indreb:alloy_smelting/bronze_ingot"
    ]
  },
  "criteria": {
    "item_copper": {
      "trigger": "minecraft:inventory_changed",
      "conditions": {
        "items": [
          {
            "items": [
              "minecraft:copper_ingot"
            ]
          }
        ]
      }
    },
    "item_tin": {
      "trigger": "minecraft:inventory_changed",
      "conditions": {
        "items": [
          {
            "items": [
              "indreb:tin_ingot"
            ]
          }
        ]
      }
    },
    "has_the_recipe": {
      "trigger": "minecraft:recipe_unlocked",
      "conditions": {
        "recipe": "indreb:alloy_smelting/bronze_ingot"
      }
    }
  },
  "requirements": [
    [
      "item_copper",
      "item_tin",
      "has_the_recipe"
    ]
  ]
}